sae_python_lib/__init__.py
sae_python_lib/arduino/__init__.py
sae_python_lib/osc/__init__.py
sae_python_lib/soundfile/__init__.py
sae_python_lib/spectral/__init__.py
sae_python_lib-1.0.0.dist-info/DESCRIPTION.rst
sae_python_lib-1.0.0.dist-info/METADATA
sae_python_lib-1.0.0.dist-info/RECORD
sae_python_lib-1.0.0.dist-info/WHEEL
sae_python_lib-1.0.0.dist-info/metadata.json
sae_python_lib-1.0.0.dist-info/top_level.txt
