Metadata-Version: 2.0
Name: sae-python-lib
Version: 1.0.0
Summary: Python library for audio signal processing
Home-page: UNKNOWN
Author: Francesco Roberto Dani
Author-email: f.r.d@hotmail.it
License: GPLv2.1
Platform: UNKNOWN
